fds/__init__.py
fds/sdk/__init__.py
fds/sdk/RealTimeNews/__init__.py
fds/sdk/RealTimeNews/api_client.py
fds/sdk/RealTimeNews/configuration.py
fds/sdk/RealTimeNews/exceptions.py
fds/sdk/RealTimeNews/model_utils.py
fds/sdk/RealTimeNews/rest.py
fds/sdk/RealTimeNews/api/__init__.py
fds/sdk/RealTimeNews/api/basic_api.py
fds/sdk/RealTimeNews/api/category_api.py
fds/sdk/RealTimeNews/api/news_api.py
fds/sdk/RealTimeNews/apis/__init__.py
fds/sdk/RealTimeNews/model/__init__.py
fds/sdk/RealTimeNews/model/attributes_member.py
fds/sdk/RealTimeNews/model/cursor_based_pagination_output_object_without_total.py
fds/sdk/RealTimeNews/model/get_basic_asset_class_list_data_items.py
fds/sdk/RealTimeNews/model/get_basic_benchmark_type_list_data_items.py
fds/sdk/RealTimeNews/model/get_basic_frequency_type_list_data_items.py
fds/sdk/RealTimeNews/model/get_basic_language_list_data_items.py
fds/sdk/RealTimeNews/model/get_basic_market_group_list_data_items.py
fds/sdk/RealTimeNews/model/get_basic_market_type_list_data_items.py
fds/sdk/RealTimeNews/model/get_basic_media_kind_list_data_items.py
fds/sdk/RealTimeNews/model/get_basic_region_continent_get_data_countries_items.py
fds/sdk/RealTimeNews/model/get_basic_region_continent_list_data_items.py
fds/sdk/RealTimeNews/model/get_basic_region_country_get_by_code_data_subdivisions_items.py
fds/sdk/RealTimeNews/model/get_basic_region_country_get_data_subdivisions_items.py
fds/sdk/RealTimeNews/model/get_basic_region_country_list_data_items.py
fds/sdk/RealTimeNews/model/get_basic_region_get_data_nested_regions_items.py
fds/sdk/RealTimeNews/model/get_basic_region_list_data_items.py
fds/sdk/RealTimeNews/model/get_basic_value_unit_alternative_list_data_items.py
fds/sdk/RealTimeNews/model/get_basic_value_unit_currency_fractional_list_data_items.py
fds/sdk/RealTimeNews/model/get_basic_value_unit_currency_fractional_list_data_items_main_currency.py
fds/sdk/RealTimeNews/model/get_category_dataset_list_data_items.py
fds.sdk.RealTimeNews-0.20.1.dist-info/LICENSE
fds.sdk.RealTimeNews-0.20.1.dist-info/METADATA
fds.sdk.RealTimeNews-0.20.1.dist-info/WHEEL
fds.sdk.RealTimeNews-0.20.1.dist-info/top_level.txt
fds.sdk.RealTimeNews-0.20.1.dist-info/RECORD
